{
  "system_configuration": {
    "num_devices": 100,
    "num_zones": 10,
    "num_rounds": 200,
    "dataset": "cifar100"
  },
  "final_performance": {
    "continuum_fl": {
      "accuracy": 0.4562,
      "loss": 2.9986804407625534,
      "total_communication_cost": 1285143.1274414062
    }
  },
  "aggregation_statistics": {
    "total_rounds": 200,
    "zone_participation_rates": {
      "zone_0": 1.0,
      "zone_1": 1.0,
      "zone_2": 1.0,
      "zone_3": 1.0,
      "zone_4": 1.0,
      "zone_5": 1.0,
      "zone_6": 1.0,
      "zone_7": 1.0,
      "zone_8": 1.0,
      "zone_9": 1.0
    },
    "average_communication_cost_mb": 6425.715637207031,
    "spatial_correlations": {
      "average": 0.9943419297624982,
      "maximum": 0.9999999992944921,
      "total_pairs": 55
    },
    "staleness_distribution": {
      "zone_0": 0,
      "zone_1": 0,
      "zone_2": 0,
      "zone_3": 0,
      "zone_4": 0,
      "zone_5": 0,
      "zone_6": 0,
      "zone_7": 0,
      "zone_8": 0,
      "zone_9": 0
    },
    "current_zone_weights": {
      "zone_0": "0.1504279",
      "zone_1": "0.14582604",
      "zone_2": "0.15371083",
      "zone_3": "0.15205228",
      "zone_4": "0.030915575",
      "zone_5": "0.097335115",
      "zone_6": "0.14422697",
      "zone_7": "0.01366326",
      "zone_8": "0.098178856",
      "zone_9": "0.01366326"
    }
  },
  "zone_discovery_statistics": {
    "rounds_completed": 1,
    "average_stability": 1.0,
    "total_migrations": 0,
    "migration_history_size": 0
  }
}